monctl/__init__.py
monctl/__main__.py
monctl/g27q.py
monctl/monctl.py
monctl/ui_monctl.py
monctl-1.0.dist-info/METADATA
monctl-1.0.dist-info/WHEEL
monctl-1.0.dist-info/licenses/LICENSE
monctl-1.0.dist-info/RECORD
